README.md
setup.py
SimpleRequestFramework/SimpleRequestFramework.py
SimpleRequestFramework/__init__.py
simple_request_framework.egg-info/PKG-INFO
simple_request_framework.egg-info/SOURCES.txt
simple_request_framework.egg-info/dependency_links.txt
simple_request_framework.egg-info/requires.txt
simple_request_framework.egg-info/top_level.txt