Metadata-Version: 2.1
Name: simple-request-framework
Version: 0.0.2
Summary: Encapsulates a framework for requests to request json corresponding package api, while saving the results locally
Home-page: https://github.com/0Chencc/
Author: 0chencc
Author-email: admin@hi-ourlife.com
License: GNU GPLv3 License
Keywords: requests,framework,api,json,save
Classifier: Programming Language :: Python :: 3
Classifier: License :: OSI Approved :: GNU General Public License v3 (GPLv3)
